bclearer_orchestration_services/__init__.py
bclearer_orchestration_services/b_app_runner_service/__init__.py
bclearer_orchestration_services/b_app_runner_service/app_startup_hard_crash_catch_wrapper_runner.py
bclearer_orchestration_services/b_app_runner_service/b_app_runner.py
bclearer_orchestration_services/b_app_runner_service/b_application_runner.py
bclearer_orchestration_services/b_app_runner_service/logging/__init__.py
bclearer_orchestration_services/b_app_runner_service/logging/application_logger_initialiser.py
bclearer_orchestration_services/b_app_runner_service/logging/application_output_folder_and_logger_set_upper.py
bclearer_orchestration_services/b_app_runner_service/logging/logger_initialiser.py
bclearer_orchestration_services/b_app_runner_service/logging/logging_ender.py
bclearer_orchestration_services/b_app_runner_service/logging/output_folder_and_logger_set_upper.py
bclearer_orchestration_services/b_app_runner_service/logging/run_logging_ender.py
bclearer_orchestration_services/b_app_runner_service/logging/run_logging_starter.py
bclearer_orchestration_services/b_eng_python_refactoring_service/__init__.py
bclearer_orchestration_services/b_eng_python_refactoring_service/b_eng_structure_and_contents/__init__.py
bclearer_orchestration_services/b_eng_python_refactoring_service/b_eng_structure_and_contents/b_eng_structure_and_content_collectors.py
bclearer_orchestration_services/b_eng_python_refactoring_service/b_eng_structure_and_contents/b_eng_content/__init__.py
bclearer_orchestration_services/b_eng_python_refactoring_service/b_eng_structure_and_contents/b_eng_content/b_eng_content_collectors.py
bclearer_orchestration_services/b_eng_python_refactoring_service/b_eng_structure_and_contents/b_eng_structure/__init__.py
bclearer_orchestration_services/b_eng_python_refactoring_service/b_eng_structure_and_contents/b_eng_structure/b_eng_child_file_structure_collectors.py
bclearer_orchestration_services-0.2.8.dist-info/METADATA
bclearer_orchestration_services-0.2.8.dist-info/WHEEL
bclearer_orchestration_services-0.2.8.dist-info/licenses/LICENSE.md
bclearer_orchestration_services-0.2.8.dist-info/RECORD
