Metadata-Version: 2.4
Name: bclearer-orchestration-services
Version: 0.2.8
Author-email: Mesbah Khan <khanm@ontoledgy.io>
License-File: LICENSE.md
Requires-Python: >=3.10
